slack_message_blocks_simplified/__init__.py
slack_message_blocks_simplified/slack_base_elements.py
slack_message_blocks_simplified/slack_blocks.py
slack_message_blocks_simplified/slack_client.py
slack_message_blocks_simplified/slack_enums.py
slack_message_blocks_simplified-0.0.11.dist-info/METADATA
slack_message_blocks_simplified-0.0.11.dist-info/WHEEL
slack_message_blocks_simplified-0.0.11.dist-info/licenses/LICENSE
slack_message_blocks_simplified-0.0.11.dist-info/RECORD
