Metadata-Version: 2.4
Name: slack_message_blocks_simplified
Version: 0.0.11
Summary: A small package that is used to create blocks in Slack messaging app
Project-URL: Github, https://github.com/Sirgogo95/slack-message-blocks-simplified.git
Author-email: Serge Celestin Taveras <sergecelestint@gmail.com>
License: Copyright (c) 2018 The Python Packaging Authority
License-File: LICENSE
Keywords: Slack
Classifier: License :: OSI Approved :: MIT License
Classifier: Operating System :: OS Independent
Classifier: Programming Language :: Python :: 3
Requires-Python: >=3.12
Requires-Dist: deprecated==1.3.1
Requires-Dist: requests==2.32.3
Requires-Dist: slack-sdk==3.37.0
